grafana_api/__init__.py
grafana_api/grafana_api.py
grafana_api/grafana_face.py
grafana_api/version.py
grafana_api/api/__init__.py
grafana_api/api/admin.py
grafana_api/api/annotations.py
grafana_api/api/base.py
grafana_api/api/dashboard.py
grafana_api/api/datasource.py
grafana_api/api/folder.py
grafana_api/api/notifications.py
grafana_api/api/organization.py
grafana_api/api/search.py
grafana_api/api/snapshots.py
grafana_api/api/team.py
grafana_api/api/user.py
test/api/__init__.py
test/api/test_admin.py
test/api/test_annotations.py
test/api/test_dashboard.py
test/api/test_folder.py
test/api/test_notifications.py
test/api/test_organization.py
test/api/test_search.py
test/api/test_snapshot.py
test/api/test_team.py
grafana_api-1.0.3.dist-info/LICENSE
grafana_api-1.0.3.dist-info/METADATA
grafana_api-1.0.3.dist-info/WHEEL
grafana_api-1.0.3.dist-info/top_level.txt
grafana_api-1.0.3.dist-info/RECORD
