Metadata-Version: 2.1
Name: grafana_api
Version: 1.0.3
Summary: Yet another Python library for Grafana API
Home-page: https://github.com/m0nhawk/grafana_api/
Author: Andrew Prokhorenkov
Author-email: andrew.prokhorenkov@gmail.com
License: MIT
Project-URL: Source, https://github.com/m0nhawk/grafana_api/
Project-URL: Tracker, https://github.com/m0nhawk/grafana_api/issues
Keywords: grafana api
Platform: UNKNOWN
Classifier: Development Status :: 4 - Beta
Classifier: Intended Audience :: Developers
Classifier: License :: OSI Approved :: MIT License
Classifier: Operating System :: OS Independent
Classifier: Programming Language :: Python :: 3
Classifier: Programming Language :: Python :: 3.6
Classifier: Programming Language :: Python :: 3.7
Classifier: Programming Language :: Python :: 3.8
Classifier: Topic :: Internet
Classifier: Topic :: Software Development
Classifier: Topic :: Software Development :: Libraries
Classifier: Topic :: Software Development :: Libraries :: Python Modules
Requires-Python: >=3.6
Provides-Extra: test
